sawp/SunbeltClient.py
sawp/__init__.py
sawp/base.py
sawp/generators/__init__.py
sawp/generators/generators.py
sawp/generators/models/__init__.py
sawp/generators/models/models.py
sawp-0.0.8.dist-info/METADATA
sawp-0.0.8.dist-info/WHEEL
sawp-0.0.8.dist-info/licenses/LICENSE.TXT
sawp-0.0.8.dist-info/RECORD
