Metadata-Version: 2.1
Name: sawp
Version: 0.0.8
Summary: A client used for interacting with the Sunbelt API.
Project-URL: Homepage, https://github.com/jacob-bayer/SAWP
Project-URL: Bug Tracker, https://github.com/jacob-bayer/SAWP/issues
Author-email: Jacob Bayer <jacobbenjaminbayer@gmail.com>
License-File: LICENSE.TXT
Classifier: License :: OSI Approved :: MIT License
Classifier: Operating System :: OS Independent
Classifier: Programming Language :: Python :: 3
Requires-Python: >=3.7
